{
  "version": "1",
  "issueId": "PAN-957",
  "created": "2026-05-07T08:33:56.381Z",
  "updated": "2026-05-07T08:33:56.404Z",
  "gitState": {},
  "decisions": [],
  "hazards": [],
  "resumePoint": null,
  "beadsMapping": {},
  "feedback": [
    {
      "seq": 1,
      "specialist": "review-agent",
      "outcome": "changes-requested",
      "timestamp": "2026-05-07T08:33:56Z",
      "markdownBody": "# Verdict: CHANGES_REQUESTED\n\n## Summary\nPR surfaces Docker service health in the workspace inspector pane: backend probes containers via `docker inspect` and active port checks, frontend chips render ✓/✗/starting icons with an expandable detail panel. Verdict is `changes_requested` because a single Blocker finding forces it: serial `docker inspect` calls on a dashboard-polled endpoint create O(n) latency. Two additional High-priority UI regressions (unknown health shown as green, uptime hidden for healthy containers) and a High-priority command-construction issue (shell-form `execAsync` in probe) should also be fixed before merge.\n\n## Blockers (MUST fix before merge)\n\n### 1. Serial `docker inspect` calls in workspace status hot path — `src/dashboard/server/routes/workspaces.ts:643` — `!`\n**Raised by**: performance\n**Why it blocks**: Dashboard polls workspace status every few seconds; each poll awaits `docker inspect` serially for every running container. A workspace with 5 containers adds 250 ms–1 s of serial subprocess latency to every request.\n\nParallelize the health probes inside `getContainerStatusAsync`. Prefer batching into a single `docker inspect <name1> <name2> ...` call and mapping results back by `.Name`, which eliminates both serial wait and repeated spawn overhead:\n\n```typescript\nconst runningNames = Object.entries(result)\n  .filter(([, info]) => info.running)\n  .map(([name]) => name);\n\nif (runningNames.length > 0) {\n  const { stdout } = await execFileAsync(\n    'docker',\n    ['inspect', ...runningNames],\n    { encoding: 'utf-8', timeout: 10000 }\n  );\n  const inspects = JSON.parse(stdout);\n  // map inspects back to result by .Name\n}\n```\n\n## High Priority (SHOULD fix; synthesis may still approve if justified)\n\n### 1. `probeContainerPortAsync` uses `execAsync` with shell-form command — `src/dashboard/server/routes/workspaces.ts:735` — `~`\n**Raised by**: correctness, security, performance\n**Why it matters**: Spawns an unnecessary host `/bin/sh` wrapper around `docker exec`, adding subprocess overhead and creating a correctness cliff if container-name constraints ever relax. The project already uses `execFileAsync` for all other Docker and `gh` invocations.\n\nReplace `execAsync` with `execFileAsync`, passing the command as an argv array:\n\n```typescript\nawait execFileAsync(\n  'docker',\n  ['exec', containerName, 'sh', '-c', probeCmd],\n  { encoding: 'utf-8', timeout: 5000 }\n);\n```\n\nThis removes the outer shell layer and keeps the probe aligned with the codebase's safer command-execution pattern.\n\n### 2. Running container with `health: 'unknown'` renders as green/success — `src/dashboard/frontend/src/components/inspector/ContainerSection.tsx:64-71` — `~`\n**Raised by**: correctness\n**Why it matters**: The `chipStyle` ternary falls through to `'badge-bg-success text-success'` for `serviceHealth === 'unknown'` (and for `undefined`). Users cannot visually distinguish a confirmed-healthy container from one with no health data.\n\nAdd an explicit `unknown` branch with a neutral style:\n\n```typescript\nserviceHealth === 'healthy' ? 'badge-bg-success text-success' :\nserviceHealth === 'unhealthy' ? 'badge-bg-destructive text-destructive' :\nserviceHealth === 'starting' ? 'badge-bg-warning text-warning animate-pulse' :\nserviceHealth === 'unknown' ? 'bg-card text-muted-foreground' :\n'badge-bg-success text-success';\n```\n\n### 3. Uptime hidden for containers with known health status — `src/dashboard/frontend/src/components/inspector/ContainerSection.tsx:95` — `~`\n**Raised by**: correctness\n**Why it matters**: The guard `(serviceHealth === 'unknown' || !serviceHealth)` suppresses uptime for healthy, unhealthy, and starting containers. This removes useful duration information from the majority of running containers.\n\nShow uptime for all running containers:\n\n```typescript\n{status.running && status.uptime && (\n  <span className=\"ml-1 text-muted-foreground\">{status.uptime}</span>\n)}\n```\n\n## Nits (advisory — safe to defer)\n\n- `src/dashboard/frontend/src/components/inspector/ContainerSection.test.tsx:98-114` — `?` — Test names claim icon verification but only assert text presence. Add assertions that query the rendered icon (by `aria-label` or `data-testid`) so removing or swapping an icon fails the test. (correctness)\n- `src/dashboard/server/routes/workspaces.ts:631` — `?` — `docker ps` filter uses `.includes(search)`, which also matches `span-957` or `pan-9570`. Pre-existing code, unchanged by this PR. Use a stricter prefix or delimiter match if touched. (correctness)\n- `src/dashboard/server/routes/workspaces.ts:~643` — `?` — Health state is recomputed on every dashboard poll. A short cache (even 5 s) would reduce `docker inspect` subprocess load ~80% under steady-state viewing. (performance)\n- `src/dashboard/frontend/src/components/inspector/ContainerSection.tsx:78-84` — Medium — Hover tooltip omits `lastProbeAt`; it is only visible after clicking to expand the detail panel. The requirements reviewer classifies this as a partial implementation gap, not a blocker, because the data is still accessible via click. Add `lastProbeAt` to the tooltip string to fully satisfy the hover/click requirement. (requirements)\n\n## Cross-cutting groups\n\n**Docker command execution hardening** (fix together):\n- [high-1] `probeContainerPortAsync` uses `execAsync` with shell-form command\n\n**ContainerSection chip rendering regressions** (fix together):\n- [high-2] Running container with `health: 'unknown'` renders as green/success\n- [high-3] Uptime hidden for containers with known health status\n\n## What's good\n- Clean separation of health-probe logic between Docker healthcheck, Traefik label parsing, and active port probes.\n- Expanded detail panel is well-structured and tested (ports, probe timestamp, failure reason).\n- Backend uses proper `execFileAsync` for `docker ps` and `docker inspect`; only the new probe path deviated.\n\n## Review stats\n- Blockers: 1   High: 3   Medium: 1   Nits: 4\n- By reviewer: correctness=3, security=0 (best-practice only), performance=2, requirements=1\n- Files touched: 4   Files with findings: 4\n\n## Appendix: individual reviews\n\nSee individual reviewer output files listed in `## Reviewer Output Files` in the Synthesis Context above. Those files contain full per-reviewer detail; this synthesis is the policy layer.\n\n## REQUIRED: Fix ALL issues above, then invoke the /rebase-and-submit skill\n\n1. Read each blocking issue carefully\n2. Fix the code for EVERY issue listed\n3. Run tests locally to verify your fixes\n4. Commit every change\n5. Invoke the /rebase-and-submit skill for PAN-957 — this is an atomic task that runs pan done (which handles rebase + push + re-submit internally)\n\nDo NOT stop between steps. Do NOT run git push manually — the skill handles it. Do NOT stop until pan done has completed successfully.\n"
    }
  ],
  "sessionHistory": [
    {
      "reason": "feedback",
      "note": "[2026-05-07T08:33Z] review-agent → CHANGES-REQUESTED — seq 1",
      "timestamp": "2026-05-07T08:33:56.381Z"
    },
    {
      "reason": "resume",
      "agentModel": "kimi-k2.6",
      "timestamp": "2026-05-07T08:33:56.404Z"
    }
  ]
}