{"version":"1.6.1","results":[[":src/components/ResourceBar.test.tsx",{"duration":53,"failed":false}],[":src/components/GodView/__tests__/GodView.test.tsx",{"duration":8,"failed":false}],[":src/hooks/__tests__/useTheme.test.ts",{"duration":60,"failed":false}],[":src/components/ResourceCard.test.tsx",{"duration":267,"failed":false}],[":src/hooks/__tests__/useSearch.test.ts",{"duration":72,"failed":false}],[":src/components/inspector/StatusHistory.test.tsx",{"duration":93,"failed":false}],[":src/components/inspector/ContainerSection.test.tsx",{"duration":99,"failed":false}],[":src/components/inspector/AgentInfoSection.test.tsx",{"duration":96,"failed":false}],[":src/components/inspector/ReviewPipelineSection.test.tsx",{"duration":88,"failed":false}],[":src/components/inspector/ActionsSection.test.tsx",{"duration":201,"failed":false}],[":src/hooks/useResourceStats.test.ts",{"duration":27,"failed":false}],[":src/components/ResourcesPanel.test.tsx",{"duration":340,"failed":false}],[":src/components/XTerminal.test.tsx",{"duration":522,"failed":false}],[":src/components/InspectorPanel.test.tsx",{"duration":9,"failed":false}],[":src/components/DialogProvider.test.tsx",{"duration":594,"failed":false}],[":src/components/KanbanBoard.test.tsx",{"duration":174,"failed":false}]]}